MANIFEST.in
README.md
setup.py
openapi_flask/__init__.py
openapi_flask/api_blueprint.py
openapi_flask/do_wrapper.py
openapi_flask/http.py
openapi_flask/markdown.py
openapi_flask/openapi.py
openapi_flask/utils.py
openapi_flask.egg-info/PKG-INFO
openapi_flask.egg-info/SOURCES.txt
openapi_flask.egg-info/dependency_links.txt
openapi_flask.egg-info/not-zip-safe
openapi_flask.egg-info/requires.txt
openapi_flask.egg-info/top_level.txt
openapi_flask/models/__init__.py
openapi_flask/models/common.py
openapi_flask/models/component.py
openapi_flask/models/file.py
openapi_flask/models/info.py
openapi_flask/models/oauth.py
openapi_flask/models/parameter.py
openapi_flask/models/path.py
openapi_flask/models/security.py
openapi_flask/models/server.py
openapi_flask/models/tag.py
openapi_flask/models/validation_error.py
openapi_flask/templates/index.html
openapi_flask/templates/rapidoc.html
openapi_flask/templates/redoc.html
openapi_flask/templates/swagger.html
openapi_flask/templates/static/css/swagger-ui.css
openapi_flask/templates/static/images/apidoc.svg
openapi_flask/templates/static/images/rapidoc.svg
openapi_flask/templates/static/images/redoc.svg
openapi_flask/templates/static/images/swagger.svg
openapi_flask/templates/static/js/rapidoc-min.js
openapi_flask/templates/static/js/redoc.standalone.js
openapi_flask/templates/static/js/swagger-ui-bundle.js
openapi_flask/templates/static/js/swagger-ui-standalone-preset.js